marshmallow_oneofschema/__init__.py
marshmallow_oneofschema/one_of_schema.py
marshmallow_oneofschema-3.0.0.dist-info/LICENSE
marshmallow_oneofschema-3.0.0.dist-info/METADATA
marshmallow_oneofschema-3.0.0.dist-info/WHEEL
marshmallow_oneofschema-3.0.0.dist-info/top_level.txt
marshmallow_oneofschema-3.0.0.dist-info/RECORD
