Metadata-Version: 2.1
Name: marshmallow-oneofschema
Version: 3.0.0
Summary: marshmallow multiplexing schema
Home-page: https://github.com/marshmallow-code/marshmallow-oneofschema
Author: Maxim Kulkin
Author-email: maxim.kulkin@gmail.com
Maintainer: Steven Loria
Maintainer-email: sloria1@gmail.com
License: MIT
Keywords: serialization,deserialization,json,marshal,marshalling,schema,validation,multiplexing,demultiplexing,polymorphic
Platform: UNKNOWN
Classifier: Intended Audience :: Developers
Classifier: License :: OSI Approved :: MIT License
Classifier: Programming Language :: Python :: 3
Classifier: Programming Language :: Python :: 3.6
Classifier: Programming Language :: Python :: 3.7
Classifier: Programming Language :: Python :: 3.8
Classifier: Programming Language :: Python :: 3.9
Requires-Python: >=3.6
License-File: LICENSE
Requires-Dist: marshmallow (<4.0.0,>=3.0.0)
Provides-Extra: dev
Requires-Dist: pytest ; extra == 'dev'
Requires-Dist: mock ; extra == 'dev'
Requires-Dist: flake8 (==3.9.2) ; extra == 'dev'
Requires-Dist: flake8-bugbear (==21.4.3) ; extra == 'dev'
Requires-Dist: pre-commit (~=2.7) ; extra == 'dev'
Requires-Dist: tox ; extra == 'dev'
Provides-Extra: lint
Requires-Dist: flake8 (==3.9.2) ; extra == 'lint'
Requires-Dist: flake8-bugbear (==21.4.3) ; extra == 'lint'
Requires-Dist: pre-commit (~=2.7) ; extra == 'lint'
Provides-Extra: tests
Requires-Dist: pytest ; extra == 'tests'
Requires-Dist: mock ; extra == 'tests'
